calipytion/__init__.py
calipytion/model.py
calipytion/ioutils/__init__.py
calipytion/ioutils/animlio.py
calipytion/tools/__init__.py
calipytion/tools/calibrator.py
calipytion/tools/enzymeml.py
calipytion/tools/equations.py
calipytion/tools/fitter.py
calipytion/tools/read_static.py
calipytion/tools/utility.py
calipytion/units/__init__.py
calipytion/units/predefined.py
calipytion-1.0.2.dist-info/METADATA
calipytion-1.0.2.dist-info/WHEEL
calipytion-1.0.2.dist-info/RECORD
