Metadata-Version: 2.4
Name: calipytion
Version: 1.0.2
Summary: Tool for creating standard curves and concentration calculations.
Author-email: haeussma <83341109+haeussma@users.noreply.github.com>
License: MIT
Requires-Python: <3.16,>=3.10
Requires-Dist: httpx>=0.25.0
Requires-Dist: lmfit>=1.0.0
Requires-Dist: matplotlib>=3.8.0
Requires-Dist: mdmodels>=0.2.0
Requires-Dist: nbformat>=5.0.0
Requires-Dist: numpy>=2.1.0
Requires-Dist: pandas[excel]<3.0,>=2.0
Requires-Dist: plotly>=6.3.0
Requires-Dist: pydantic>=2.0.0
Requires-Dist: pyenzyme>=2.1.0
Requires-Dist: rich>=13.0.0
Requires-Dist: sympy>=1.0.0
Requires-Dist: toml>=0.10.2
